{
    "funFacts": [
        {
            "author": "602651056320675840",
            "content": "test",
            "imageURL": "",
            "created": 1605747526820
        },
        {
            "author": "602651056320675840",
            "content": "test with a screenshot",
            "imageURL": "https://cdn.discordapp.com/attachments/771191044192731197/778787644032417873/unknown.png",
            "created": 1605747574837
        },
        {
            "author": "602651056320675840",
            "content": "eggs",
            "imageURL": "",
            "created": 1607653645037
        },
        {
            "author": "528309195116642314",
            "content": "This command belonged to oh no, #JusticeForOhNo",
            "imageURL": "",
            "created": 1607653676645
        }
    ]
}